cursor_prompts-1.0.0.dist-info/licenses/LICENSE
prompt_analyzer/__init__.py
prompt_analyzer/analysis/__init__.py
prompt_analyzer/analysis/analyzer.py
prompt_analyzer/analysis/detector.py
prompt_analyzer/analysis/scorer.py
prompt_analyzer/analysis/similarity.py
prompt_analyzer/analysis/suggestions.py
prompt_analyzer/cli/__init__.py
prompt_analyzer/cli/commands.py
prompt_analyzer/cli/main.py
prompt_analyzer/cli/setup.py
prompt_analyzer/hooks/__init__.py
prompt_analyzer/hooks/generator.py
prompt_analyzer/hooks/installer.py
prompt_analyzer/storage/__init__.py
prompt_analyzer/storage/config.py
prompt_analyzer/storage/crud.py
prompt_analyzer/storage/database.py
prompt_analyzer/storage/filters.py
prompt_analyzer/storage/paths.py
prompt_analyzer/ui/__init__.py
prompt_analyzer/ui/formatters.py
cursor_prompts-1.0.0.dist-info/METADATA
cursor_prompts-1.0.0.dist-info/WHEEL
cursor_prompts-1.0.0.dist-info/entry_points.txt
cursor_prompts-1.0.0.dist-info/top_level.txt
cursor_prompts-1.0.0.dist-info/RECORD
