Metadata-Version: 2.4
Name: cursor-prompts
Version: 1.0.0
Summary: A local-first tool that captures and analyzes Cursor prompts for quality and effectiveness
Author: Cursor Prompts Contributors
License: MIT
Keywords: cursor,prompt,analysis,ai,ide,developer-tools
Classifier: Development Status :: 4 - Beta
Classifier: Intended Audience :: Developers
Classifier: License :: OSI Approved :: MIT License
Classifier: Programming Language :: Python :: 3
Classifier: Programming Language :: Python :: 3.8
Classifier: Programming Language :: Python :: 3.9
Classifier: Programming Language :: Python :: 3.10
Classifier: Programming Language :: Python :: 3.11
Classifier: Programming Language :: Python :: 3.12
Requires-Python: >=3.8
License-File: LICENSE
Requires-Dist: click>=8.0.0
Requires-Dist: thefuzz>=0.19.0
Provides-Extra: dev
Requires-Dist: pytest>=7.0.0; extra == "dev"
Requires-Dist: pytest-cov>=4.0.0; extra == "dev"
Dynamic: license-file
